netset.py
netset-0.0.2.dist-info/DESCRIPTION.rst
netset-0.0.2.dist-info/METADATA
netset-0.0.2.dist-info/RECORD
netset-0.0.2.dist-info/WHEEL
netset-0.0.2.dist-info/entry_points.txt
netset-0.0.2.dist-info/metadata.json
netset-0.0.2.dist-info/top_level.txt
