Metadata-Version: 2.0
Name: netset
Version: 0.0.2
Summary: A network configuration tool for the commandline, written in Python.
Home-page: https://github.com/MrLeeh/netset.py
Author: UNKNOWN
Author-email: UNKNOWN
License: MIT
Keywords: network
Platform: UNKNOWN
Classifier: Development Status :: 2 - Pre-Alpha
Classifier: Environment :: Console
Classifier: Intended Audience :: Developers
Classifier: License :: OSI Approved :: MIT License
Classifier: Operating System :: Microsoft :: Windows
Classifier: Programming Language :: Python :: 3.6
Classifier: Topic :: System :: Networking
Classifier: Topic :: Utilities
Requires-Dist: click (>=6.7)
Requires-Dist: pypiwin32 (>=220)
Requires-Dist: tabulate (>=0.7.7)
Requires-Dist: wmi (>=1.4.9)
